shdatetime/__init__.py
shdatetime-0.1.0.dist-info/LICENSE.txt
shdatetime-0.1.0.dist-info/WHEEL
shdatetime-0.1.0.dist-info/METADATA
shdatetime-0.1.0.dist-info/RECORD
