Metadata-Version: 2.1
Name: shdatetime
Version: 0.1.0
Summary: Solar Hijri datetime for Python
Keywords: shdatetime,datetime,Solar Hijri,calendar
Requires-Python: >= 3.12
Requires-Dist: gshconverter
Requires-Dist: jdatetime ; extra == "test"
Project-URL: Homepage, https://github.com/5j9/shdatetime
Provides-Extra: test
